README.txt
bootstrap.py
buildout.cfg
setup.py
docs/HISTORY.txt
rpatterson/__init__.py
rpatterson.stripdupes.egg-info/PKG-INFO
rpatterson.stripdupes.egg-info/SOURCES.txt
rpatterson.stripdupes.egg-info/dependency_links.txt
rpatterson.stripdupes.egg-info/entry_points.txt
rpatterson.stripdupes.egg-info/namespace_packages.txt
rpatterson.stripdupes.egg-info/not-zip-safe
rpatterson.stripdupes.egg-info/requires.txt
rpatterson.stripdupes.egg-info/top_level.txt
rpatterson/stripdupes/README.txt
rpatterson/stripdupes/__init__.py
rpatterson/stripdupes/bar.txt
rpatterson/stripdupes/foo.txt
rpatterson/stripdupes/tests.py