Metadata-Version: 1.0
Name: rpatterson.stripdupes
Version: 0.1
Summary: Strip duplicated sequences of lines from within files
Home-page: http://pypi.python.org/pypi/rpatterson.stripdupes
Author: Ross Patterson
Author-email: me@rpatterson.net
License: GPL
Platform: UNKNOWN
Classifier: Programming Language :: Python
Classifier: Topic :: Software Development :: Libraries :: Python Modules
